wordprexit/__init__.py
wordprexit/autop.py
wordprexit/cli.py
wordprexit/hugo_shortcodes.py
wordprexit/wp_shortcodes.py
wordprexit/wxrfile.py
wordprexit-0.0.2.dist-info/LICENSE
wordprexit-0.0.2.dist-info/METADATA
wordprexit-0.0.2.dist-info/WHEEL
wordprexit-0.0.2.dist-info/entry_points.txt
wordprexit-0.0.2.dist-info/top_level.txt
wordprexit-0.0.2.dist-info/RECORD
